dfllama/__init__.py
dfllama/client.py
dfllama/dtypes.py
dfllama/exc.py
dfllama/log.py
dfllama/resources/coingecko_ids.json
dfllama/utils.py
dfllama-0.1.8.dist-info/LICENSE
dfllama-0.1.8.dist-info/METADATA
dfllama-0.1.8.dist-info/WHEEL
dfllama-0.1.8.dist-info/RECORD
