Metadata-Version: 2.1
Name: dfllama
Version: 0.1.8
Summary: Python Api Wrapper for DefiLlama API
Home-page: https://github.com/JakubPluta/defillama/
License: MIT
Author: Jakub Pluta
Author-email: plutakuba@gmail.com
Requires-Python: >=3.10,<4.0
Classifier: License :: OSI Approved :: MIT License
Classifier: Operating System :: OS Independent
Classifier: Programming Language :: Python :: 3
Classifier: Programming Language :: Python :: 3.10
Classifier: Programming Language :: Python :: 3.11
Classifier: Programming Language :: Python :: 3.12
Requires-Dist: python-slugify (>=8.0.1,<9.0.0)
Project-URL: Repository, https://github.com/JakubPluta/defillama/
